{"assets":{"4F2CE7081AEAD05D7481C6E79BF2BC38":{"type":"texture","index":7,"assetRequest":{"type":"slide","state":"contents","slide":"none"},"url":{"native":"assets\/3CDBE0CB-B912-435B-975B-63BB489D816D.pdf"},"width":1920,"height":880},"2A3AC8A00A66E2C7A162E0EDCEB6552B":{"type":"texture","index":1,"assetRequest":{"type":"slide","state":"contents","slide":"none"},"url":{"native":"assets\/3CDBE0CB-B912-435B-975B-63BB489D816D.pdf"},"width":2164,"height":904},"71D6985F5D7FF0533082BDC84ED9716D":{"type":"texture","index":3,"assetRequest":{"type":"slide","state":"contents","slide":"none"},"url":{"native":"assets\/3CDBE0CB-B912-435B-975B-63BB489D816D.pdf"},"width":467,"height":458},"D97F0122132F1E3D684085514D6D418D":{"type":"texture","index":6,"assetRequest":{"type":"slide","state":"contents","slide":"none"},"url":{"native":"assets\/3CDBE0CB-B912-435B-975B-63BB489D816D.pdf"},"width":1920,"height":880},"giphy (8).gif-0.0000-2.5200":{"type":"video","index":0,"assetRequest":{"type":"slide","state":"contents","slide":"none"},"url":{"web":"assets\/giphy (8).gif-0.0000-2.5200.gif","native":"assets\/giphy (8).gif-0.0000-2.5200.gif"},"width":480,"height":200},"EEE8BF27D22FB293294DF796BC56F910":{"type":"texture","index":2,"assetRequest":{"type":"slide","state":"contents","slide":"none"},"url":{"native":"assets\/3CDBE0CB-B912-435B-975B-63BB489D816D.pdf"},"width":15,"height":15},"A2828440EAE9E5F6B1689A7C6CE3A5F7":{"type":"texture","index":0,"assetRequest":{"type":"slide","state":"contents","slide":"none"},"url":{"native":"assets\/3CDBE0CB-B912-435B-975B-63BB489D816D.pdf"},"width":1920,"height":880},"AF1A45D06DFAB2243597452592213604":{"type":"texture","index":4,"assetRequest":{"type":"slide","state":"contents","slide":"none"},"url":{"native":"assets\/3CDBE0CB-B912-435B-975B-63BB489D816D.pdf"},"width":335,"height":423},"7AF8947DABB6E2F8EC20AA30C78EC233":{"url":{"native":"assets\/3CDBE0CB-B912-435B-975B-63BB489D816D.pdf"},"height":900.2899169921875,"movie":"giphy (8).gif-0.0000-2.5200","width":2160.69580078125,"type":"texture","assetRequest":{"type":"slide","state":"contents","slide":"none"},"index":5}},"events":[{"effects":[{"beginTime":0,"baseLayer":{"animations":[],"initialState":{"affineTransform":[1,0,0,1,0,0],"masksToBounds":false,"rotation":0,"scale":1,"position":{"pointX":1051.821317672729,"pointY":441.8550415039062},"width":2164,"sublayerTransform":[1,0,0,0,0,1,0,0,0,0,1,0,0,0,0,1],"contentsRect":{"y":0,"x":0,"width":1,"height":1},"opacity":1,"edgeAntialiasingMask":251658240,"height":904,"hidden":false,"anchorPoint":{"pointX":0.5,"pointY":0.5}},"objectID":"622C1E76-DB01-4640-9B96-EA09BE4E6AB5","layers":[{"animations":[],"initialState":{"affineTransform":[1,0,0,1,0,0],"masksToBounds":false,"rotation":0,"scale":1,"position":{"pointX":990.1786823272705,"pointY":450.1449584960938},"width":2164,"sublayerTransform":[1,0,0,0,0,1,0,0,0,0,1,-0.0004296425620922507,0,0,0,1],"contentsRect":{"y":0,"x":0,"width":1,"height":1},"opacity":1,"edgeAntialiasingMask":251658240,"height":904,"hidden":false,"anchorPoint":{"pointX":0.4575687071752637,"pointY":0.4979479629381568}},"layers":[{"animations":[{"timeOffset":0,"beginTime":1e-100,"animations":[{"timeOffset":0,"from":{"scalar":true},"beginTime":0,"repeatCount":0,"fillMode":"removed","property":"isPlaying","autoreverses":false,"duration":0.01,"to":{"scalar":true}},{"timeOffset":0,"from":{"scalar":false},"beginTime":0,"repeatCount":0,"fillMode":"removed","property":"hidden","autoreverses":false,"duration":0.01,"to":{"scalar":false}}],"repeatCount":0,"duration":0.01,"autoreverses":false,"fillMode":"both"}],"layers":[],"texturedRectangle":{"isBackgroundTexture":true,"singleTextureOpacity":1,"textureType":5,"textBaseline":0,"textXHeight":0,"isVerticalText":false},"initialState":{"affineTransform":[1,0,0,1,0,0],"masksToBounds":false,"rotation":0,"scale":1,"position":{"pointX":1080.178682327271,"pointY":450.1449584960938},"width":2164,"sublayerTransform":[1,0,0,0,0,1,0,0,0,0,1,0,0,0,0,1],"contentsRect":{"y":0,"x":0,"width":1,"height":1},"opacity":1,"edgeAntialiasingMask":0,"height":904,"hidden":false,"anchorPoint":{"pointX":0.5,"pointY":0.5}},"texture":"2A3AC8A00A66E2C7A162E0EDCEB6552B"}]}]},"effects":[{"beginTime":0,"baseLayer":{"animations":[],"initialState":{"affineTransform":[1,0,0,1,0,0],"masksToBounds":false,"rotation":0,"scale":1,"position":{"pointX":1050.169218063354,"pointY":440},"width":2160.69580078125,"sublayerTransform":[1,0,0,0,0,1,0,0,0,0,1,0,0,0,0,1],"contentsRect":{"y":0,"x":0,"width":1,"height":1},"opacity":1,"edgeAntialiasingMask":251658240,"height":900.2899169921875,"hidden":false,"anchorPoint":{"pointX":0.5,"pointY":0.5}},"objectID":"622C1E76-DB01-4640-9B96-EA09BE4E6AB5","layers":[{"animations":[],"layers":[],"texturedRectangle":{"isBackgroundTexture":true,"singleTextureOpacity":1,"textureType":5,"textBaseline":0,"textXHeight":0,"isVerticalText":false},"initialState":{"affineTransform":[1,0,0,1,0,0],"masksToBounds":false,"rotation":0,"scale":1,"position":{"pointX":1080.178682327271,"pointY":450.1449584960938},"width":2164,"sublayerTransform":[1,0,0,0,0,1,0,0,0,0,1,0,0,0,0,1],"contentsRect":{"y":0,"x":0,"width":1,"height":1},"opacity":1,"edgeAntialiasingMask":0,"height":904,"hidden":true,"anchorPoint":{"pointX":0.5,"pointY":0.5}},"texture":"2A3AC8A00A66E2C7A162E0EDCEB6552B"},{"animations":[],"layers":[],"isVideoLayer":true,"initialState":{"affineTransform":[1,0,0,1,0,0],"masksToBounds":false,"rotation":0,"scale":1,"position":{"pointX":1080.347900390625,"pointY":450.1449584960938},"width":2160.69580078125,"sublayerTransform":[1,0,0,0,0,1,0,0,0,0,1,0,0,0,0,1],"contentsRect":{"y":0,"x":0,"width":1,"height":1},"opacity":1,"edgeAntialiasingMask":251658240,"height":900.2899169921875,"hidden":false,"anchorPoint":{"pointX":0.5,"pointY":0.5}},"texture":"7AF8947DABB6E2F8EC20AA30C78EC233"}]},"effects":[],"movie":{"volume":1,"isStreaming":false,"isAudioOnly":false,"endTime":2.519999980926514,"startTime":0,"asset":"giphy (8).gif-0.0000-2.5200","loopMode":"looping"},"duration":0,"type":"buildIn","name":"renderMovie","objectID":"622C1E76-DB01-4640-9B96-EA09BE4E6AB5"}],"duration":0.01,"type":"buildIn","name":"apple:movie-start","objectID":"622C1E76-DB01-4640-9B96-EA09BE4E6AB5"}],"automaticPlay":true,"hyperlinks":[],"accessibility":[{"text":"sound","targetRectangle":{"y":213.7772099813933,"x":66.05508242896929,"width":306.1499995641411,"height":121.8999815583229}},{"text":"design","targetRectangle":{"y":320.3972151228897,"x":50.97508252582679,"width":321.2299994672836,"height":121.8999815583229}},{"text":"and ","targetRectangle":{"y":427.0172202643862,"x":187.2150822352542,"width":202.7999996609985,"height":121.8999815583229}},{"text":"music","targetRectangle":{"y":533.6372254058826,"x":90.62508242896928,"width":278.3299995157123,"height":121.8999815583229}},{"text":"￼","targetRectangle":{"y":829.7396010011435,"x":954.495,"width":11.00999999999999,"height":20.92499680817127}},{"text":"We’re pulling shots from lots of different movies and TV shows, which all have very different soundscapes. Obviously, there’s a wealth of iconic music in the MCU. We have a lot of options if we want to stick with a track that’s already established with the brand. Since the music is responsible for carrying the momentum of both their world and ours I want a sound that’s positive, not too serious, and unifying. I’ve thought a little bit about how we might incorporate Endgame’s score because it has the most character motifs assembled in a single musical piece.","targetRectangle":{"y":195.6732504193376,"x":407.8775909104827,"width":463.732116699219,"height":468.0000185966492}}],"baseLayer":{"animations":[],"initialState":{"affineTransform":[1,0,0,1,0,0],"masksToBounds":false,"rotation":0,"scale":1,"position":{"pointX":960,"pointY":440},"width":1920,"sublayerTransform":[1,0,0,0,0,1,0,0,0,0,1,0,0,0,0,1],"contentsRect":{"y":0,"x":0,"width":1,"height":1},"opacity":1,"edgeAntialiasingMask":251658240,"height":880,"hidden":false,"anchorPoint":{"pointX":0.5,"pointY":0.5}},"layers":[{"animations":[],"initialState":{"affineTransform":[1,0,0,1,0,0],"masksToBounds":false,"rotation":0,"scale":1,"position":{"pointX":960,"pointY":440},"width":1920,"sublayerTransform":[1,0,0,0,0,1,0,0,0,0,1,0,0,0,0,1],"contentsRect":{"y":0,"x":0,"width":1,"height":1},"opacity":1,"edgeAntialiasingMask":251658240,"height":880,"hidden":false,"anchorPoint":{"pointX":0.5,"pointY":0.5}},"layers":[{"animations":[],"initialState":{"affineTransform":[1,0,0,1,0,0],"masksToBounds":false,"rotation":0,"scale":1,"position":{"pointX":960,"pointY":440},"width":1920,"sublayerTransform":[1,0,0,0,0,1,0,0,0,0,1,0,0,0,0,1],"contentsRect":{"y":0,"x":0,"width":1,"height":1},"opacity":1,"edgeAntialiasingMask":251658240,"height":880,"hidden":false,"anchorPoint":{"pointX":0.5,"pointY":0.5}},"layers":[{"animations":[],"layers":[],"texturedRectangle":{"isBackgroundTexture":true,"singleTextureOpacity":1,"textureType":1,"textBaseline":0,"textXHeight":0,"isVerticalText":false},"initialState":{"affineTransform":[1,0,0,1,0,0],"masksToBounds":false,"rotation":0,"scale":1,"position":{"pointX":960,"pointY":440},"width":1920,"sublayerTransform":[1,0,0,0,0,1,0,0,0,0,1,0,0,0,0,1],"contentsRect":{"y":0,"x":0,"width":1,"height":1},"opacity":1,"edgeAntialiasingMask":0,"height":880,"hidden":false,"anchorPoint":{"pointX":0.5,"pointY":0.5}},"texture":"A2828440EAE9E5F6B1689A7C6CE3A5F7"}]}]},{"animations":[],"initialState":{"affineTransform":[1,0,0,1,0,0],"masksToBounds":false,"rotation":0,"scale":1,"position":{"pointX":960,"pointY":440},"width":1920,"sublayerTransform":[1,0,0,0,0,1,0,0,0,0,1,0,0,0,0,1],"contentsRect":{"y":0,"x":0,"width":1,"height":1},"opacity":1,"edgeAntialiasingMask":251658240,"height":880,"hidden":false,"anchorPoint":{"pointX":0.5,"pointY":0.5}},"layers":[{"animations":[],"initialState":{"affineTransform":[1,0,0,1,0,0],"masksToBounds":false,"rotation":0,"scale":1,"position":{"pointX":1051.821317672729,"pointY":441.8550415039062},"width":2164,"sublayerTransform":[1,0,0,0,0,1,0,0,0,0,1,0,0,0,0,1],"contentsRect":{"y":0,"x":0,"width":1,"height":1},"opacity":1,"edgeAntialiasingMask":251658240,"height":904,"hidden":false,"anchorPoint":{"pointX":0.5,"pointY":0.5}},"objectID":"622C1E76-DB01-4640-9B96-EA09BE4E6AB5","layers":[{"animations":[],"layers":[],"texturedRectangle":{"isBackgroundTexture":true,"singleTextureOpacity":1,"textureType":5,"textBaseline":0,"textXHeight":0,"isVerticalText":false},"initialState":{"affineTransform":[1,0,0,1,0,0],"masksToBounds":false,"rotation":0,"scale":1,"position":{"pointX":1080.178682327271,"pointY":450.1449584960938},"width":2164,"sublayerTransform":[1,0,0,0,0,1,0,0,0,0,1,0,0,0,0,1],"contentsRect":{"y":0,"x":0,"width":1,"height":1},"opacity":1,"edgeAntialiasingMask":0,"height":904,"hidden":false,"anchorPoint":{"pointX":0.5,"pointY":0.5}},"texture":"2A3AC8A00A66E2C7A162E0EDCEB6552B"}]}]},{"animations":[],"initialState":{"affineTransform":[1,0,0,1,0,0],"masksToBounds":false,"rotation":0,"scale":1,"position":{"pointX":960,"pointY":440},"width":1920,"sublayerTransform":[1,0,0,0,0,1,0,0,0,0,1,0,0,0,0,1],"contentsRect":{"y":0,"x":0,"width":1,"height":1},"opacity":1,"edgeAntialiasingMask":251658240,"height":880,"hidden":false,"anchorPoint":{"pointX":0.5,"pointY":0.5}},"layers":[{"animations":[],"initialState":{"affineTransform":[1,0,0,1,0,0],"masksToBounds":false,"rotation":0,"scale":1,"position":{"pointX":888.1222534179688,"pointY":833.9803417772055},"width":15,"sublayerTransform":[1,0,0,0,0,1,0,0,0,0,1,0,0,0,0,1],"contentsRect":{"y":0,"x":0,"width":1,"height":1},"opacity":1,"edgeAntialiasingMask":251658240,"height":15,"hidden":false,"anchorPoint":{"pointX":0.5,"pointY":0.5}},"layers":[{"animations":[],"layers":[],"texturedRectangle":{"singleTextureOpacity":1,"textXHeight":0.5429999999999999,"textBaseline":0.8459728529055913,"isBackgroundTexture":true,"isVerticalText":false,"textColor":[0.9999100565910339,1,0.9998779892921448,1],"textureType":6},"initialState":{"affineTransform":[1,0,0,1,0,0],"masksToBounds":false,"rotation":0,"scale":1,"position":{"pointX":78.87774658203125,"pointY":9.019658222794533},"width":15,"sublayerTransform":[1,0,0,0,0,1,0,0,0,0,1,0,0,0,0,1],"contentsRect":{"y":0,"x":0,"width":1,"height":1},"opacity":1,"edgeAntialiasingMask":0,"height":15,"hidden":false,"anchorPoint":{"pointX":0.5,"pointY":0.5}},"texture":"EEE8BF27D22FB293294DF796BC56F910"}]}]},{"animations":[],"initialState":{"affineTransform":[1,0,0,1,0,0],"masksToBounds":false,"rotation":0,"scale":1,"position":{"pointX":960,"pointY":440},"width":1920,"sublayerTransform":[1,0,0,0,0,1,0,0,0,0,1,0,0,0,0,1],"contentsRect":{"y":0,"x":0,"width":1,"height":1},"opacity":1,"edgeAntialiasingMask":251658240,"height":880,"hidden":false,"anchorPoint":{"pointX":0.5,"pointY":0.5}},"layers":[{"animations":[],"initialState":{"affineTransform":[1,0,0,1,0,0],"masksToBounds":false,"rotation":0,"scale":1,"position":{"pointX":641.3775909104827,"pointY":269.6732504193376},"width":467,"sublayerTransform":[1,0,0,0,0,1,0,0,0,0,1,0,0,0,0,1],"contentsRect":{"y":0,"x":0,"width":1,"height":1},"opacity":1,"edgeAntialiasingMask":251658240,"height":458,"hidden":false,"anchorPoint":{"pointX":0.5,"pointY":0.5}},"layers":[{"animations":[],"layers":[],"texturedRectangle":{"singleTextureOpacity":1,"textXHeight":0.02392139737991266,"textBaseline":1.062491982746764,"isBackgroundTexture":true,"isVerticalText":false,"textColor":[0.9999100565910339,1,0.9998779892921448,1],"textureType":6},"initialState":{"affineTransform":[1,0,0,1,0,0],"masksToBounds":false,"rotation":0,"scale":1,"position":{"pointX":231.6224090895172,"pointY":387.3267495806624},"width":467,"sublayerTransform":[1,0,0,0,0,1,0,0,0,0,1,0,0,0,0,1],"contentsRect":{"y":0,"x":0,"width":1,"height":1},"opacity":1,"edgeAntialiasingMask":0,"height":458,"hidden":false,"anchorPoint":{"pointX":0.5,"pointY":0.5}},"texture":"71D6985F5D7FF0533082BDC84ED9716D"}]}]},{"animations":[],"initialState":{"affineTransform":[1,0,0,1,0,0],"masksToBounds":false,"rotation":0,"scale":1,"position":{"pointX":960,"pointY":440},"width":1920,"sublayerTransform":[1,0,0,0,0,1,0,0,0,0,1,0,0,0,0,1],"contentsRect":{"y":0,"x":0,"width":1,"height":1},"opacity":1,"edgeAntialiasingMask":251658240,"height":880,"hidden":false,"anchorPoint":{"pointX":0.5,"pointY":0.5}},"layers":[{"animations":[],"initialState":{"affineTransform":[1,0,0,1,0,0],"masksToBounds":false,"rotation":0,"scale":1,"position":{"pointX":41.17626333735126,"pointY":241.6938764891143},"width":335,"sublayerTransform":[1,0,0,0,0,1,0,0,0,0,1,0,0,0,0,1],"contentsRect":{"y":0,"x":0,"width":1,"height":1},"opacity":1,"edgeAntialiasingMask":251658240,"height":423,"hidden":false,"anchorPoint":{"pointX":0.5,"pointY":0.5}},"layers":[{"animations":[],"layers":[],"texturedRectangle":{"singleTextureOpacity":1,"textXHeight":0.1668794326241135,"textBaseline":0.9918136034839233,"isBackgroundTexture":true,"isVerticalText":false,"textColor":[0.8656144738197327,0.209461584687233,0.1804208308458328,1],"textureType":6},"initialState":{"affineTransform":[1,0,0,1,0,0],"masksToBounds":false,"rotation":0,"scale":1,"position":{"pointX":347.8237366626487,"pointY":391.3061235108858},"width":335,"sublayerTransform":[1,0,0,0,0,1,0,0,0,0,1,0,0,0,0,1],"contentsRect":{"y":0,"x":0,"width":1,"height":1},"opacity":1,"edgeAntialiasingMask":0,"height":423,"hidden":false,"anchorPoint":{"pointX":0.5,"pointY":0.5}},"texture":"AF1A45D06DFAB2243597452592213604"}]}]}]}},{"effects":[{"beginTime":0,"baseLayer":{"animations":[],"initialState":{"affineTransform":[1,0,0,1,0,0],"masksToBounds":false,"rotation":0,"scale":1,"position":{"pointX":960,"pointY":440},"width":1920,"sublayerTransform":[1,0,0,0,0,1,0,0,0,0,1,0,0,0,0,1],"contentsRect":{"y":0,"x":0,"width":1,"height":1},"opacity":1,"edgeAntialiasingMask":251658240,"height":880,"hidden":false,"anchorPoint":{"pointX":0.5,"pointY":0.5}},"objectID":"0","layers":[{"animations":[],"initialState":{"affineTransform":[1,0,0,1,0,0],"masksToBounds":false,"rotation":0,"scale":1,"position":{"pointX":960,"pointY":440},"width":1920,"sublayerTransform":[1,0,0,0,0,1,0,0,0,0,1,-0.0004296425620922507,0,0,0,1],"contentsRect":{"y":0,"x":0,"width":1,"height":1},"opacity":1,"edgeAntialiasingMask":251658240,"height":880,"hidden":false,"anchorPoint":{"pointX":0.5,"pointY":0.5}},"layers":[{"animations":[],"layers":[],"texturedRectangle":{"isBackgroundTexture":false,"singleTextureOpacity":1,"textureType":0,"textBaseline":0,"textXHeight":0,"isVerticalText":false},"initialState":{"affineTransform":[1,0,0,1,0,0],"masksToBounds":false,"rotation":0,"scale":1,"position":{"pointX":960,"pointY":440},"width":1920,"sublayerTransform":[1,0,0,0,0,1,0,0,0,0,1,0,0,0,0,1],"contentsRect":{"y":0,"x":0,"width":1,"height":1},"opacity":1,"edgeAntialiasingMask":0,"height":880,"hidden":false,"anchorPoint":{"pointX":0.5,"pointY":0.5}},"texture":"4F2CE7081AEAD05D7481C6E79BF2BC38"},{"animations":[{"timeOffset":0,"from":{"scalar":false},"beginTime":0,"repeatCount":0,"fillMode":"both","property":"hidden","autoreverses":false,"duration":0.01,"to":{"scalar":true}}],"layers":[],"texturedRectangle":{"isBackgroundTexture":false,"singleTextureOpacity":1,"textureType":0,"textBaseline":0,"textXHeight":0,"isVerticalText":false},"initialState":{"affineTransform":[1,0,0,1,0,0],"masksToBounds":false,"rotation":0,"scale":1,"position":{"pointX":960,"pointY":440},"width":1920,"sublayerTransform":[1,0,0,0,0,1,0,0,0,0,1,0,0,0,0,1],"contentsRect":{"y":0,"x":0,"width":1,"height":1},"opacity":1,"edgeAntialiasingMask":0,"height":880,"hidden":false,"anchorPoint":{"pointX":0.5,"pointY":0.5}},"texture":"D97F0122132F1E3D684085514D6D418D"}]}]},"effects":[],"duration":0.01,"type":"transition","name":"none","objectID":"0"}],"automaticPlay":false,"hyperlinks":[],"accessibility":[{"text":"sound","targetRectangle":{"y":213.7772099813933,"x":66.05508242896929,"width":306.1499995641411,"height":121.8999815583229}},{"text":"design","targetRectangle":{"y":320.3972151228897,"x":50.97508252582679,"width":321.2299994672836,"height":121.8999815583229}},{"text":"and ","targetRectangle":{"y":427.0172202643862,"x":187.2150822352542,"width":202.7999996609985,"height":121.8999815583229}},{"text":"music","targetRectangle":{"y":533.6372254058826,"x":90.62508242896928,"width":278.3299995157123,"height":121.8999815583229}},{"text":"￼","targetRectangle":{"y":829.7396010011435,"x":954.495,"width":11.00999999999999,"height":20.92499680817127}},{"text":"We’re pulling shots from lots of different movies and TV shows, which all have very different soundscapes. Obviously, there’s a wealth of iconic music in the MCU. We have a lot of options if we want to stick with a track that’s already established with the brand. Since the music is responsible for carrying the momentum of both their world and ours I want a sound that’s positive, not too serious, and unifying. I’ve thought a little bit about how we might incorporate Endgame’s score because it has the most character motifs assembled in a single musical piece.","targetRectangle":{"y":195.6732504193376,"x":407.8775909104827,"width":463.732116699219,"height":468.0000185966492}}],"baseLayer":{"animations":[],"initialState":{"affineTransform":[1,0,0,1,0,0],"masksToBounds":false,"rotation":0,"scale":1,"position":{"pointX":960,"pointY":440},"width":1920,"sublayerTransform":[1,0,0,0,0,1,0,0,0,0,1,0,0,0,0,1],"contentsRect":{"y":0,"x":0,"width":1,"height":1},"opacity":1,"edgeAntialiasingMask":251658240,"height":880,"hidden":false,"anchorPoint":{"pointX":0.5,"pointY":0.5}},"objectID":"0","layers":[{"animations":[],"initialState":{"affineTransform":[1,0,0,1,0,0],"masksToBounds":false,"rotation":0,"scale":1,"position":{"pointX":960,"pointY":440},"width":1920,"sublayerTransform":[1,0,0,0,0,1,0,0,0,0,1,-0.0004296425620922507,0,0,0,1],"contentsRect":{"y":0,"x":0,"width":1,"height":1},"opacity":1,"edgeAntialiasingMask":251658240,"height":880,"hidden":false,"anchorPoint":{"pointX":0.5,"pointY":0.5}},"layers":[{"animations":[],"layers":[],"texturedRectangle":{"isBackgroundTexture":false,"singleTextureOpacity":1,"textureType":0,"textBaseline":0,"textXHeight":0,"isVerticalText":false},"initialState":{"affineTransform":[1,0,0,1,0,0],"masksToBounds":false,"rotation":0,"scale":1,"position":{"pointX":960,"pointY":440},"width":1920,"sublayerTransform":[1,0,0,0,0,1,0,0,0,0,1,0,0,0,0,1],"contentsRect":{"y":0,"x":0,"width":1,"height":1},"opacity":1,"edgeAntialiasingMask":0,"height":880,"hidden":false,"anchorPoint":{"pointX":0.5,"pointY":0.5}},"texture":"D97F0122132F1E3D684085514D6D418D"}]}]}}]}